youcos/__init__.py
youcos/scrape_youtube.py
youcos/test.py
youcos/yt_requests.py
youcos-0.0.6.dist-info/LICENSE
youcos-0.0.6.dist-info/METADATA
youcos-0.0.6.dist-info/WHEEL
youcos-0.0.6.dist-info/top_level.txt
youcos-0.0.6.dist-info/RECORD
