Metadata-Version: 2.1
Name: youcos
Version: 0.0.6
Summary: youcos is a simple Python package for collecting YouTube videos and comments
Home-page: https://github.com/seungguini/youcos
Author: Seunggun Lee
Author-email: seungguini@gmail.com
License: MIT
Platform: UNKNOWN
Classifier: License :: OSI Approved :: MIT License
Classifier: Programming Language :: Python
Classifier: Programming Language :: Python :: 3.5
Classifier: Programming Language :: Python :: 3.6
Classifier: Topic :: Software Development :: Libraries
Classifier: Topic :: Software Development :: Libraries :: Python Modules
Classifier: Intended Audience :: Developers
Requires-Python: >=3.5
Requires-Dist: selenium
Requires-Dist: google-api-python-client
